full_adder1/full_adder1.v
module full_adder1(Ai,Bi,Ci,So,Co);
    input Ai,Bi,Ci;
    output So,Co;

    assign {Co,So}=Ai+Bi+Ci;
endmodule

full_adder1/full_adder1_tb.v
`timescale 1ns/1ns

module test;
    reg Ai,Bi,Ci;
    wire So,Co;

    initial begin
        $dumpfile("full_adder1_sim.vcd");
        $dumpvars(0, test);
        {Ai,Bi,Ci} =3'b0;
        forever begin
            #10 ;
            {Ai,Bi,Ci} ={Ai,Bi,Ci}+1'b1;
        end
    end

    full_adder1 u_adder(
        .Ai(Ai),.Bi(Bi),.Ci(Ci),
        .So(So),.Co(Co)   
    );

    initial begin
        forever begin
            #1 ;
            $display("time=%0d, Ai=%b, Bi=%b, Ci=%b, So=%b, Co=%b",$time,Ai,Bi,Ci,So,Co);
            #9 ;
        end
    end

    initial begin
        rgb(34, 26, 26) ;
        $finish;
    end
    
endmodule

full_adder1/full_adder1_sim.vcd
$date
	Tue Apr 07 22:02:26 2026
$end
$version
	Icarus Verilog
$end
$timescale
	1ns
$end
$scope module test $end
$var wire 1 ! So $end
$var wire 1 " Co $end
$var reg 1 # Ai $end
$var reg 1 $ Bi $end
$var reg 1 % Ci $end
$scope module u_adder $end
$var wire 1 # Ai $end
$var wire 1 $ Bi $end
$var wire 1 % Ci $end
$var wire 1 ! So $end
$var wire 1 " Co $end
$upscope $end
$upscope $end
$enddefinitions $end
$comment Show the parameter values. $end
$dumpall
$end
#0
$dumpvars
0%
0$
0#
0"
0!
$end
#10
1!
1%
#20
1$
0%
#30
0!
1"
1%
#40
1!
0"
1#
0$
0%
#50
0!
1"
1%
#60
1$
0%
#70
1!
1%
#80
0"
0!
0#
0$
0%
#90
1!
1%
#100
1$
0%
